robot_browser/__init__.py
robot_browser/browser_extension.py
robot_browser/index.py
robot_browser/playwright_browser.py
robot_browser/utils.py
robot_browser-0.3.4.dist-info/METADATA
robot_browser-0.3.4.dist-info/WHEEL
robot_browser-0.3.4.dist-info/RECORD
