Metadata-Version: 2.4
Name: robot_browser
Version: 0.3.4
Summary: robot browser tools
Author: mance
Classifier: License :: OSI Approved :: MIT License
Classifier: Operating System :: OS Independent
Classifier: Programming Language :: Python :: 3
Requires-Python: >=3.11
Requires-Dist: ddddocr
Requires-Dist: loguru
Requires-Dist: playwright
Requires-Dist: pyrect
Requires-Dist: websocket-client
